{
  "cli": {
    "version": "18.4.0"
  },
  "build": {
    "development": {
      "developmentClient": true,
      "distribution": "internal",
      "channel": "development",
      "env": {
        "EXPO_PUBLIC_REVENUECAT_APPLE_KEY": "appl_ttiiqmHPmKTuvfALCxMccyWRjcE",
        "EXPO_PUBLIC_REVENUECAT_GOOGLE_KEY": "goog_qpsKxRjYMoggqPCnnJBukFkeFbq",
        "EXPO_PUBLIC_REVENUECAT_TEST_KEY": "test_ySGTdedRmOLfYFyuTHWENpeZmiX",
        "EXPO_PUBLIC_BACKEND_URL": "https://clutch-picks-production.up.railway.app",
        "BACKEND_URL": "https://clutch-picks-production.up.railway.app",
        "EXPO_IOS_BUILD_NUMBER": "52"
      },
      "ios": {
        "simulator": false
      }
    },
    "preview": {
      "distribution": "internal",
      "channel": "preview",
      "env": {
        "EXPO_PUBLIC_REVENUECAT_APPLE_KEY": "appl_ttiiqmHPmKTuvfALCxMccyWRjcE",
        "EXPO_PUBLIC_REVENUECAT_GOOGLE_KEY": "goog_qpsKxRjYMoggqPCnnJBukFkeFbq",
        "EXPO_PUBLIC_REVENUECAT_TEST_KEY": "test_ySGTdedRmOLfYFyuTHWENpeZmiX",
        "EXPO_PUBLIC_BACKEND_URL": "https://clutch-picks-production.up.railway.app",
        "BACKEND_URL": "https://clutch-picks-production.up.railway.app",
        "EXPO_IOS_BUILD_NUMBER": "53"
      },
      "ios": {
        "simulator": false
      }
    },
    "production": {
      "channel": "production",
      "env": {
        "EXPO_PUBLIC_REVENUECAT_APPLE_KEY": "appl_ttiiqmHPmKTuvfALCxMccyWRjcE",
        "EXPO_PUBLIC_REVENUECAT_GOOGLE_KEY": "goog_qpsKxRjYMoggqPCnnJBukFkeFbq",
        "EXPO_PUBLIC_REVENUECAT_TEST_KEY": "test_ySGTdedRmOLfYFyuTHWENpeZmiX",
        "EXPO_PUBLIC_BACKEND_URL": "https://clutch-picks-production.up.railway.app",
        "BACKEND_URL": "https://clutch-picks-production.up.railway.app",
        "EXPO_IOS_BUILD_NUMBER": "65"
      },
      "ios": {
        "distribution": "store",
        "image": "macos-sequoia-15.6-xcode-26.0"
      },
      "android": {
        "distribution": "store"
      }
    }
  },
  "submit": {
    "production": {
      "ios": {
        "ascAppId": "6759183746"
      }
    }
  }
}
